falai_mcp/__init__.py
falai_mcp/config.py
falai_mcp/fal.py
falai_mcp/main.py
falai_mcp/model_index.py
falai_mcp/server.py
falai_mcp_tools-0.2.2.dist-info/licenses/LICENSE
falai_mcp_tools-0.2.2.dist-info/METADATA
falai_mcp_tools-0.2.2.dist-info/WHEEL
falai_mcp_tools-0.2.2.dist-info/entry_points.txt
falai_mcp_tools-0.2.2.dist-info/top_level.txt
falai_mcp_tools-0.2.2.dist-info/RECORD
