Metadata-Version: 2.4
Name: falai-mcp-tools
Version: 0.2.2
Summary: FastMCP server exposing fal.ai model APIs
Author-email: Berk Birkan <berkbirkan@example.com>
Maintainer-email: Berk Birkan <berkbirkan@example.com>
License-Expression: MIT
Project-URL: Homepage, https://github.com/berkbirkan/falai-mcp
Project-URL: Repository, https://github.com/berkbirkan/falai-mcp
Project-URL: Issues, https://github.com/berkbirkan/falai-mcp/issues
Keywords: mcp,fal.ai,ai,model,api,server
Classifier: Development Status :: 4 - Beta
Classifier: Intended Audience :: Developers
Classifier: Operating System :: OS Independent
Classifier: Programming Language :: Python :: 3
Classifier: Programming Language :: Python :: 3.10
Classifier: Programming Language :: Python :: 3.11
Classifier: Programming Language :: Python :: 3.12
Classifier: Topic :: Software Development :: Libraries :: Python Modules
Classifier: Topic :: Internet :: WWW/HTTP :: HTTP Servers
Requires-Python: >=3.10
License-File: LICENSE
Requires-Dist: mcp>=1.0.0
Requires-Dist: fal-client>=0.4.0
Requires-Dist: httpx<1.0.0,>=0.21.0
Dynamic: license-file
